am_filler/__init__.py
am_filler/categorical.py
am_filler/core.py
am_filler/numeric.py
am_filler/text.py
am_filler/utils.py
am_filler-1.0.0.dist-info/licenses/LICENSE
am_filler-1.0.0.dist-info/METADATA
am_filler-1.0.0.dist-info/WHEEL
am_filler-1.0.0.dist-info/top_level.txt
am_filler-1.0.0.dist-info/RECORD
