Metadata-Version: 2.4
Name: am_filler
Version: 1.0.0
Summary: Intelligent, automatic missing value imputation library for pandas datasets with context-aware text handling.
Home-page: https://github.com/MudassarGill/AM_filler
Author: Mudassar Hussain
Author-email: Mudassar Hussain <mudassarjutt65030@gmail.com>
License: MIT
Project-URL: Homepage, https://github.com/MudassarGill/AM_filler
Project-URL: Bug Reports, https://github.com/MudassarGill/AM_filler/issues
Project-URL: Source, https://github.com/MudassarGill/AM_filler
Keywords: missing values,imputation,data cleaning,pandas,machine learning,preprocessing,automl
Classifier: Development Status :: 4 - Beta
Classifier: Intended Audience :: Developers
Classifier: Intended Audience :: Science/Research
Classifier: License :: OSI Approved :: MIT License
Classifier: Operating System :: OS Independent
Classifier: Programming Language :: Python :: 3
Classifier: Programming Language :: Python :: 3.8
Classifier: Programming Language :: Python :: 3.9
Classifier: Programming Language :: Python :: 3.10
Classifier: Programming Language :: Python :: 3.11
Classifier: Programming Language :: Python :: 3.12
Classifier: Topic :: Scientific/Engineering :: Artificial Intelligence
Classifier: Topic :: Software Development :: Libraries :: Python Modules
Requires-Python: >=3.8
License-File: LICENSE
Requires-Dist: pandas>=1.3.0
Requires-Dist: numpy>=1.20.0
Requires-Dist: scipy>=1.7.0
Provides-Extra: dev
Requires-Dist: pytest>=7.0.0; extra == "dev"
Requires-Dist: pytest-cov>=4.0.0; extra == "dev"
Provides-Extra: ml
Requires-Dist: scikit-learn>=1.0.0; extra == "ml"
Dynamic: author
Dynamic: home-page
Dynamic: license-file
Dynamic: requires-python
